aioeloverblik/__init__.py
aioeloverblik/client.py
aioeloverblik/exceptions.py
aioeloverblik/models.py
aioeloverblik-0.1.2.dist-info/METADATA
aioeloverblik-0.1.2.dist-info/WHEEL
aioeloverblik-0.1.2.dist-info/licenses/LICENSE
aioeloverblik-0.1.2.dist-info/RECORD
