Metadata-Version: 2.4
Name: aioeloverblik
Version: 0.1.2
Summary: Async Python wrapper for Eloverblik.dk API (Customer & ThirdParty)
Project-URL: Repository, https://github.com/will2022/aioeloverblik
Project-URL: Changelog, https://github.com/will2022/aioeloverblik/blob/main/CHANGELOG.md
Author-email: William <william@heitech.dk>
License-Expression: MIT
License-File: LICENSE
Classifier: Development Status :: 3 - Alpha
Classifier: Intended Audience :: Developers
Classifier: License :: OSI Approved :: MIT License
Classifier: Programming Language :: Python :: 3
Classifier: Programming Language :: Python :: 3.9
Classifier: Programming Language :: Python :: 3.10
Classifier: Programming Language :: Python :: 3.11
Classifier: Programming Language :: Python :: 3.12
Requires-Python: >=3.9
Requires-Dist: httpx>=0.28.1
Requires-Dist: pydantic<3.0.0,>=2.10.0
Provides-Extra: dev
Requires-Dist: pytest-asyncio>=1.3.0; extra == 'dev'
Requires-Dist: pytest>=9.0.2; extra == 'dev'
Requires-Dist: python-dotenv>=1.2.1; extra == 'dev'
Requires-Dist: respx>=0.22.0; extra == 'dev'
Requires-Dist: ruff>=0.14.10; extra == 'dev'
